MANIFEST.in
README
README.rst
setup.py
PyBabel_hbs.egg-info/PKG-INFO
PyBabel_hbs.egg-info/SOURCES.txt
PyBabel_hbs.egg-info/dependency_links.txt
PyBabel_hbs.egg-info/entry_points.txt
PyBabel_hbs.egg-info/requires.txt
PyBabel_hbs.egg-info/top_level.txt
pybabel_hbs/__init__.py
pybabel_hbs/extract_i18n.coffee
pybabel_hbs/extract_i18n.js
pybabel_hbs/extractor.py
pybabel_hbs/lib/custom_handlebars.js