Metadata-Version: 1.0
Name: PyBabel-hbs
Version: 0.2.1
Summary: PyBabel handlebars gettext strings extractor
Home-page: https://github.com/tigrawap/pybabel-hbs
Author: Anton Bykov aka Tigra San
Author-email: tigrawap@gmail.com
License: UNKNOWN
Platform: UNKNOWN
